tinycoinlib/__init__.py
tinycoinlib/receive.py
tinycoinlib/send.py
tinycoinlib/talk.py
tinycoinlib/version.py
tinycoinlib-0.0.1.dist-info/LICENSE
tinycoinlib-0.0.1.dist-info/METADATA
tinycoinlib-0.0.1.dist-info/WHEEL
tinycoinlib-0.0.1.dist-info/top_level.txt
tinycoinlib-0.0.1.dist-info/RECORD
