Metadata-Version: 2.1
Name: tinycoinlib
Version: 0.0.1
Summary: Any coin (Bitcoin, Litecoin, Dogecoin..) RPC client and utilities for Python.
Home-page: https://github.com/bigcoinboy/tinycoinlib
Author: BigCoinBoy
Author-email: bigcoinboy@protonmail.com
License: GPLv3
Project-URL: Bug Tracker, https://github.com/bigcoinboy/tinycoinlib/issues
Platform: any
Classifier: Programming Language :: Python :: 3
Classifier: Development Status :: 2 - Pre-Alpha
Classifier: License :: OSI Approved :: GNU General Public License v3 (GPLv3)
Classifier: Operating System :: OS Independent
Classifier: Topic :: Software Development :: Libraries
Classifier: Topic :: Utilities
Requires-Python: >=3
License-File: LICENSE
